cloud_info_provider/__init__.py
cloud_info_provider/core.py
cloud_info_provider/exceptions.py
cloud_info_provider/glue.py
cloud_info_provider/utils.py
cloud_info_provider/formatters/__init__.py
cloud_info_provider/formatters/base.py
cloud_info_provider/formatters/glue.py
cloud_info_provider/providers/__init__.py
cloud_info_provider/providers/base.py
cloud_info_provider/providers/openstack.py
cloud_info_provider/providers/utils.py
cloud_info_provider/publishers/__init__.py
cloud_info_provider/publishers/base.py
cloud_info_provider/publishers/stdout.py
cloud_info_provider/tests/__init__.py
cloud_info_provider/tests/base.py
cloud_info_provider/tests/data.py
cloud_info_provider/tests/test_base_provider.py
cloud_info_provider/tests/test_core.py
cloud_info_provider/tests/test_gocdb.py
cloud_info_provider/tests/test_openstack.py
cloud_info_provider/tests/test_publishers.py
cloud_info_provider/tests/utils.py
cloud_info_provider-1.0.2.dist-info/METADATA
cloud_info_provider-1.0.2.dist-info/WHEEL
cloud_info_provider-1.0.2.dist-info/entry_points.txt
cloud_info_provider-1.0.2.dist-info/licenses/AUTHORS
cloud_info_provider-1.0.2.dist-info/licenses/LICENSE.txt
cloud_info_provider-1.0.2.dist-info/RECORD
