Metadata-Version: 2.4
Name: cloud-info-provider
Version: 1.0.2
Summary: A cloud information discovery tool for EGI FedCloud
Author-email: Enol Fernandez <enol.fernandez@egi.eu>, Baptiste Grenier <baptiste.grenier@egi.eu>, Alvaro Lopez <aloga@ifca.unican.es>, Andre Gemuend <andre.gemuend@scai.fraunhofer.de>, Bjorn Hagemeier <b.hagemeier@fz-juelich.de>, Boris Parak <parak@cesnet.cz>, Bruce Becker <bruce.becker@egi.eu>, Carlos Gimeno Yanez <cgimeno@bifi.es>, Pablo Orviz <orviz@ifca.unican.es>, Ruben Diez <rdiez@cesga.es>, Salvatore Pinto <salvatore.pinto@egi.eu>
License-File: AUTHORS
License-File: LICENSE.txt
Requires-Python: >=3.10
Requires-Dist: defusedxml>=0.7.1
Requires-Dist: keystoneauth1>=5.9.1
Requires-Dist: pydantic>=2.11.3
Requires-Dist: pyopenssl>=25.1.0
Requires-Dist: python-dateutil>=2.9.0.post0
Requires-Dist: python-glanceclient>=4.7.0
Requires-Dist: python-keystoneclient>=5.5.0
Requires-Dist: python-novaclient>=18.7.0
Requires-Dist: pyyaml>=6.0.2
Requires-Dist: requests>=2.32.4
Requires-Dist: stevedore>=5.4.0
